[{"name":"iSvrqu","marks":65},{"name":"7ONeqEjbjk","marks":85},{"name":"Y0trj5uCX","marks":31},{"name":"drn8OB","marks":48},{"name":"v8lKVE0","marks":42},{"name":"oG08t","marks":65},{"name":"mMfOB","marks":82},{"name":"C9sMrEQVM","marks":8},{"name":"IGPBxU","marks":92},{"name":"LpfQUwn","marks":49},{"name":"4nz9Q9NMQ","marks":24},{"name":"8ZxCcHrN7","marks":64},{"name":"MbS","marks":48},{"name":"TScx9","marks":35},{"name":"skGRgIrpeE","marks":64},{"name":"YZKaOkqK","marks":68},{"name":"Pfk4UM","marks":58},{"name":"Ny3ha8BM","marks":91},{"name":"T","marks":26},{"name":"Gvr9SnSCRX","marks":59},{"name":"hxpr0ipMRU","marks":88},{"name":"af2ll","marks":55},{"name":"nL2WEUQ8Q","marks":93},{"name":"IvJxKCIF5f","marks":63},{"name":"kR2","marks":73},{"name":"ODlD","marks":86},{"name":"znXv","marks":97},{"name":"lVMm04J9gM","marks":71},{"name":"N","marks":56},{"name":"xWW","marks":23},{"name":"jw","marks":26},{"name":"A02","marks":90},{"name":"X","marks":5},{"name":"1","marks":36},{"name":"irqv70ZpQ","marks":12},{"name":"5aIPnVEbg","marks":60},{"name":"CcCdzCwg","marks":1},{"name":"H2YiEDf","marks":32},{"name":"eBjjn5Bf1V","marks":15},{"name":"unVyK","marks":46},{"name":"K9zC","marks":27},{"name":"5RiwZVgEdZ","marks":66},{"name":"E7u","marks":55},{"name":"ISVVa940","marks":88},{"name":"oV","marks":67},{"name":"col89","marks":40},{"name":"ikI","marks":41},{"name":"fOEc78","marks":49},{"name":"8zZJDSJmi","marks":26},{"name":"ry7IZCS","marks":29},{"name":"n6f","marks":56},{"name":"xRqS8Sxz","marks":42},{"name":"Bma","marks":37},{"name":"df","marks":17},{"name":"2O490M8","marks":34},{"name":"VN","marks":8},{"name":"LlESy4vK","marks":41},{"name":"iK","marks":31},{"name":"IxdUYz","marks":91},{"name":"TMt0uB7","marks":98},{"name":"fT0flRk4Bl","marks":18},{"name":"qr","marks":86},{"name":"V4iXzwKz","marks":2},{"name":"KHCT4P","marks":0},{"name":"m3yuqn0","marks":80},{"name":"c","marks":84},{"name":"ZDNFbh","marks":41},{"name":"SM10Tq6UWQ","marks":29},{"name":"68h6","marks":38},{"name":"FJQI","marks":71},{"name":"xT8WirfPn","marks":42},{"name":"WY","marks":62},{"name":"pWB","marks":27},{"name":"AKZHtxuP","marks":6},{"name":"4k53kKSVg","marks":20},{"name":"tuHHI","marks":90},{"name":"qLp8Uzgvd","marks":21},{"name":"MT","marks":59},{"name":"eks","marks":87},{"name":"ZUTv","marks":38},{"name":"iDyZHVN0R8","marks":60},{"name":"32LIvWZhEX","marks":72},{"name":"gxoXF","marks":90},{"name":"64QnvY6Tr","marks":63},{"name":"s6VF4NO1W","marks":85},{"name":"bqm3tl","marks":48},{"name":"2K3n80G","marks":42},{"name":"WY41jM","marks":44},{"name":"k9hvQSPhC","marks":48},{"name":"rue2ScG","marks":46},{"name":"6KC","marks":89},{"name":"iXoH7D3Ne","marks":65},{"name":"DN","marks":20},{"name":"doTNO","marks":58},{"name":"8XJi","marks":81},{"name":"j1bZa4xd","marks":79},{"name":"wvwr2xb","marks":82},{"name":"V3IO9UL7Dr","marks":11},{"name":"UU","marks":23},{"name":"L1L4E","marks":21}]